README.txt
TODO
kqueuemodule.c
pykqueue.txt
setup.py
test1.py
py_kqueue.egg-info/PKG-INFO
py_kqueue.egg-info/SOURCES.txt
py_kqueue.egg-info/dependency_links.txt
py_kqueue.egg-info/not-zip-safe
py_kqueue.egg-info/top_level.txt