Metadata-Version: 1.0
Name: py-kqueue
Version: 2.0.1
Summary: This is a kqueue package
Home-page: UNKNOWN
Author: Jaromir Dolecek
Author-email: jdolecek@netbsd.org
License: UNKNOWN
Platform: UNKNOWN
